{
  "subtitle": "", 
  "description": "", 
  "language": "nep_NP", 
  "title": "\u0938\u092e\u094d\u092a\u0930\u094d\u0915:", 
  "primary_category": null, 
  "created_at": "2015-02-27T05:02:54+00:00", 
  "featured_in_category": false, 
  "modified_at": "2016-02-13T10:10:43.297235+00:00", 
  "_version": {
    "package_version": "0.3.7", 
    "language_version": "2.7.6", 
    "language_version_string": "2.7.6 (default, Mar 22 2014, 23:03:41) \n[GCC 4.8.2]", 
    "language": "python", 
    "package": "elastic-git"
  }, 
  "linked_pages": [], 
  "id": null, 
  "content": "\u0924\u092a\u093e\u0908\u0901\u0932\u0947 \u0938\u093e\u0907\u091f\u092e\u093e \u0916\u094b\u091c\u0947\u0915\u094b \u0915\u0941\u0930\u093e \u092a\u093e\u0909\u0928\u0941\u092d\u092f\u094b? \u092f\u0939\u093e\u0901 \u0915\u0947\u0939\u0940 \u0915\u0941\u0930\u093e \u0925\u092a\u094d\u0928\u0941 \u091b \u092d\u0928\u0947 \u0939\u093e\u092e\u0940\u0932\u093e\u0908 \u092d\u0928\u094d\u0928\u0941\u0939\u094b\u0938\u094d\u0964\r\n\r\n\u0939\u093e\u092e\u0940\u0932\u093e\u0908 (Hello@girleffect.org ) \u0907\u092e\u0947\u0932 \u0917\u0930\u094d\u0928\u0941\u0939\u094b\u0938\u094d \r\n\r\n[FACEBOOK][1] \u092e\u093e \u0932\u093e\u0907\u0915 \u0917\u0930\u094d\u0928\u0941\u0939\u094b\u0938\u094d\r\n\r\n\r\n  [1]: http://www.facebook.com/girleffect", 
  "source": "2750021fbfee427b8ce8656fccd78ad5", 
  "featured": false, 
  "author_tags": [], 
  "image": null, 
  "published": null, 
  "position": 0, 
  "image_host": "http://thumbor.unicore.io", 
  "slug": "contact", 
  "uuid": "492befdc6a1f443490adfadc8607d8e8"
}